snuh/__init__.py
snuh-0.1.0.dist-info/LICENSE
snuh-0.1.0.dist-info/METADATA
snuh-0.1.0.dist-info/WHEEL
snuh-0.1.0.dist-info/top_level.txt
snuh-0.1.0.dist-info/RECORD
